README.md
setup.py
netcrypt/__init__.py
netcrypt/communication.py
netcrypt/cryptography.py
netcrypt.egg-info/PKG-INFO
netcrypt.egg-info/SOURCES.txt
netcrypt.egg-info/dependency_links.txt
netcrypt.egg-info/requires.txt
netcrypt.egg-info/top_level.txt