Metadata-Version: 1.0
Name: netcrypt
Version: 1.0.0a1
Summary: simplifying socket data stream cryptography using RSA public keys and AES data encryption
Home-page: https://github.com/nsk89/netcrypt
Author: Nathaniel Knous
Author-email: nsk89@live.com
License: BSD 2-Clause
Platform: UNKNOWN
